LICENSE
MANIFEST.in
README.md
README.rst
setup.py
methylmap/__init__.py
methylmap/annotation.py
methylmap/dendro.py
methylmap/import_data.py
methylmap/methylmap.py
methylmap/plots.py
methylmap/process_1000Genomes.py
methylmap/region.py
methylmap/version.py
methylmap.egg-info/PKG-INFO
methylmap.egg-info/SOURCES.txt
methylmap.egg-info/dependency_links.txt
methylmap.egg-info/entry_points.txt
methylmap.egg-info/requires.txt
methylmap.egg-info/top_level.txt
scripts/calculate_methylation_frequency.py
scripts/split_calls_by_phase.py